pycsw_rpi/admin.py
pycsw_rpi/apiso.py
pycsw_rpi/config.py
pycsw_rpi/metadata.py
pycsw_rpi/repository.py
pycsw_rpi/server.py
pycsw_rpi/wsgi.py
pycsw_rpi-0.1.6.dist-info/METADATA
pycsw_rpi-0.1.6.dist-info/WHEEL
pycsw_rpi-0.1.6.dist-info/entry_points.txt
pycsw_rpi-0.1.6.dist-info/RECORD
