Metadata-Version: 2.1
Name: pycsw-rpi
Version: 0.1.6
Summary: PyCSW monkey patched for Slovak national catalogue service
Home-page: https://gitlab.com/mzpsr/minzp/geocloud.sk/applications/pycsw-rpi
License: MIT
Author: Peter Mozolík
Author-email: petermozolik@gmail.com
Requires-Python: >=3.8,<4.0
Classifier: License :: OSI Approved :: MIT License
Classifier: Programming Language :: Python :: 3
Classifier: Programming Language :: Python :: 3.8
Classifier: Programming Language :: Python :: 3.9
Classifier: Programming Language :: Python :: 3.10
Classifier: Programming Language :: Python :: 3.11
Classifier: Programming Language :: Python :: 3.12
Requires-Dist: SQLAlchemy (>=1.4,<2.0)
Requires-Dist: pycsw (>=2.6,<3.0)
Requires-Dist: setuptools (>=74.1.2,<75.0.0)
Project-URL: Repository, https://gitlab.com/mzpsr/minzp/geocloud.sk/applications/pycsw-rpi
